[{"date": "2025-04-30", "symbol": "DOCU", "reportedCurrency": "USD", "cik": "0001261333", "fillingDate": "2025-06-06", "acceptedDate": "2025-06-06 16:06:36", "calendarYear": "2026", "period": "Q1", "netIncome": 72087000, "depreciationAndAmortization": 30369000, "deferredIncomeTax": -3465000, "stockBasedCompensation": 145596000, "changeInWorkingCapital": -66151000, "accountsReceivables": 121003000, "inventory": 0, "accountsPayables": -6764000, "otherWorkingCapital": -180390000, "otherNonCashItems": 73003000, "netCashProvidedByOperatingActivities": 251439000, "investmentsInPropertyPlantAndEquipment": -23624000, "acquisitionsNet": 0, "purchasesOfInvestments": -92563000, "salesMaturitiesOfInvestments": 91262000, "otherInvestingActivites": 0, "netCashUsedForInvestingActivites": -24925000, "debtRepayment": -4969000, "commonStockIssued": 0, "commonStockRepurchased": -183431000, "dividendsPaid": 0, "otherFinancingActivites": -40084000, "netCashUsedProvidedByFinancingActivities": -223515000, "effectOfForexChangesOnCash": 9923000, "netChangeInCash": 12922000, "cashAtEndOfPeriod": 672476000, "cashAtBeginningOfPeriod": 659554000, "operatingCashFlow": 251439000, "capitalExpenditure": -23624000, "freeCashFlow": 227815000, "link": "https://www.sec.gov/Archives/edgar/data/1261333/000126133325000075/0001261333-25-000075-index.htm", "finalLink": "https://www.sec.gov/Archives/edgar/data/1261333/000126133325000075/docu-20250430.htm"}, {"date": "2025-01-31", "symbol": "DOCU", "reportedCurrency": "USD", "cik": "0001261333", "fillingDate": "2025-03-18", "acceptedDate": "2025-03-18 16:13:20", "calendarYear": "2025", "period": "Q4", "netIncome": 83491000, "depreciationAndAmortization": 28707000, "deferredIncomeTax": -22103000, "stockBasedCompensation": 149947000, "changeInWorkingCapital": -996000, "accountsReceivables": -128616000, "inventory": 0, "accountsPayables": 9152000, "otherWorkingCapital": 118468000, "otherNonCashItems": 68866000, "netCashProvidedByOperatingActivities": 307912000, "investmentsInPropertyPlantAndEquipment": -28342000, "acquisitionsNet": -143611000, "purchasesOfInvestments": -78449000, "salesMaturitiesOfInvestments": 74500000, "otherInvestingActivites": 143611000, "netCashUsedForInvestingActivites": -32291000, "debtRepayment": 0, "commonStockIssued": 0, "commonStockRepurchased": -161725000, "dividendsPaid": 0, "otherFinancingActivites": -69789000, "netCashUsedProvidedByFinancingActivities": -231514000, "effectOfForexChangesOnCash": -5311000, "netChangeInCash": 38796000, "cashAtEndOfPeriod": 659554000, "cashAtBeginningOfPeriod": 620758000, "operatingCashFlow": 307912000, "capitalExpenditure": -28342000, "freeCashFlow": 279570000, "link": "https://www.sec.gov/Archives/edgar/data/1261333/000126133325000024/0001261333-25-000024-index.htm", "finalLink": "https://www.sec.gov/Archives/edgar/data/1261333/000126133325000024/docu-20250131.htm"}, {"date": "2024-10-31", "symbol": "DOCU", "reportedCurrency": "USD", "cik": "0001261333", "fillingDate": "2024-12-06", "acceptedDate": "2024-12-06 16:05:52", "calendarYear": "2025", "period": "Q3", "netIncome": 0, "depreciationAndAmortization": 27569000, "deferredIncomeTax": 6675000, "stockBasedCompensation": 153228000, "changeInWorkingCapital": -82721000, "accountsReceivables": 7120000, "inventory": 0, "accountsPayables": 10061000, "otherWorkingCapital": -99902000, "otherNonCashItems": 46854000, "netCashProvidedByOperatingActivities": 234326000, "investmentsInPropertyPlantAndEquipment": -23613000, "acquisitionsNet": 0, "purchasesOfInvestments": -110296000, "salesMaturitiesOfInvestments": 90211000, "otherInvestingActivites": -20085000, "netCashUsedForInvestingActivites": -43698000, "debtRepayment": 0, "commonStockIssued": 0, "commonStockRepurchased": -172665000, "dividendsPaid": 0, "otherFinancingActivites": -25670000, "netCashUsedProvidedByFinancingActivities": -198335000, "effectOfForexChangesOnCash": 438000, "netChangeInCash": -7269000, "cashAtEndOfPeriod": 620758000, "cashAtBeginningOfPeriod": 628027000, "operatingCashFlow": 234326000, "capitalExpenditure": -23613000, "freeCashFlow": 210713000, "link": "https://www.sec.gov/Archives/edgar/data/1261333/000126133324000151/0001261333-24-000151-index.htm", "finalLink": "https://www.sec.gov/Archives/edgar/data/1261333/000126133324000151/docu-20241031.htm"}, {"date": "2024-07-31", "symbol": "DOCU", "reportedCurrency": "USD", "cik": "0001261333", "fillingDate": "2024-09-06", "acceptedDate": "2024-09-06 16:06:21", "calendarYear": "2025", "period": "Q2", "netIncome": 888211000, "depreciationAndAmortization": 27022000, "deferredIncomeTax": -826038000, "stockBasedCompensation": 164656000, "changeInWorkingCapital": -99872000, "accountsReceivables": 0, "inventory": 0, "accountsPayables": -10412000, "otherWorkingCapital": -89460000, "otherNonCashItems": 66229000, "netCashProvidedByOperatingActivities": 220208000, "investmentsInPropertyPlantAndEquipment": -22280000, "acquisitionsNet": -143611000, "purchasesOfInvestments": -103728000, "salesMaturitiesOfInvestments": 93509000, "otherInvestingActivites": -10219000, "netCashUsedForInvestingActivites": -176110000, "debtRepayment": 0, "commonStockIssued": 0, "commonStockRepurchased": -200076000, "dividendsPaid": 0, "otherFinancingActivites": -39446000, "netCashUsedProvidedByFinancingActivities": -239068000, "effectOfForexChangesOnCash": 238000, "netChangeInCash": -194732000, "cashAtEndOfPeriod": 628027000, "cashAtBeginningOfPeriod": 822759000, "operatingCashFlow": 220208000, "capitalExpenditure": -22280000, "freeCashFlow": 197928000, "link": "https://www.sec.gov/Archives/edgar/data/1261333/000126133324000121/0001261333-24-000121-index.htm", "finalLink": "https://www.sec.gov/Archives/edgar/data/1261333/000126133324000121/docu-20240731.htm"}, {"date": "2024-04-30", "symbol": "DOCU", "reportedCurrency": "USD", "cik": "0001261333", "fillingDate": "2024-06-07", "acceptedDate": "2024-06-07 16:37:57", "calendarYear": "2025", "period": "Q1", "netIncome": 33760000, "depreciationAndAmortization": 24506000, "deferredIncomeTax": 1477000, "stockBasedCompensation": 142504000, "changeInWorkingCapital": -8121000, "accountsReceivables": 130639000, "inventory": 0, "accountsPayables": -1163000, "otherWorkingCapital": -137597000, "otherNonCashItems": 122740000, "netCashProvidedByOperatingActivities": 254826000, "investmentsInPropertyPlantAndEquipment": -22753000, "acquisitionsNet": 0, "purchasesOfInvestments": -120138000, "salesMaturitiesOfInvestments": 82114000, "otherInvestingActivites": -38024000, "netCashUsedForInvestingActivites": -60777000, "debtRepayment": 0, "commonStockIssued": 0, "commonStockRepurchased": -149062000, "dividendsPaid": 0, "otherFinancingActivites": -20812000, "netCashUsedProvidedByFinancingActivities": -169874000, "effectOfForexChangesOnCash": -2915000, "netChangeInCash": 24396000, "cashAtEndOfPeriod": 822788000, "cashAtBeginningOfPeriod": 798392000, "operatingCashFlow": 254826000, "capitalExpenditure": -22753000, "freeCashFlow": 232073000, "link": "https://www.sec.gov/Archives/edgar/data/1261333/000126133324000087/0001261333-24-000087-index.htm", "finalLink": "https://www.sec.gov/Archives/edgar/data/1261333/000126133324000087/docu-20240430.htm"}, {"date": "2024-01-31", "symbol": "DOCU", "reportedCurrency": "USD", "cik": "0001261333", "fillingDate": "2024-03-21", "acceptedDate": "2024-03-21 16:30:09", "calendarYear": "2024", "period": "Q4", "netIncome": 27241000, "depreciationAndAmortization": 28444000, "deferredIncomeTax": -973000, "stockBasedCompensation": 161016000, "changeInWorkingCapital": 27391000, "accountsReceivables": -81221000, "inventory": -8482000, "accountsPayables": 4263000, "otherWorkingCapital": 104349000, "otherNonCashItems": 52858000, "netCashProvidedByOperatingActivities": 295977000, "investmentsInPropertyPlantAndEquipment": -22114000, "acquisitionsNet": -89352000, "purchasesOfInvestments": -133000000, "salesMaturitiesOfInvestments": 222352000, "otherInvestingActivites": 89352000, "netCashUsedForInvestingActivites": 67238000, "debtRepayment": -689896000, "commonStockIssued": 784000, "commonStockRepurchased": 0, "dividendsPaid": 0, "otherFinancingActivites": -45922000, "netCashUsedProvidedByFinancingActivities": -760313000, "effectOfForexChangesOnCash": 5096000, "netChangeInCash": -391518000, "cashAtEndOfPeriod": 797060000, "cashAtBeginningOfPeriod": 1188578000, "operatingCashFlow": 295977000, "capitalExpenditure": -22114000, "freeCashFlow": 273863000, "link": "https://www.sec.gov/Archives/edgar/data/1261333/000126133324000045/0001261333-24-000045-index.htm", "finalLink": "https://www.sec.gov/Archives/edgar/data/1261333/000126133324000045/docu-20240131.htm"}, {"date": "2023-10-31", "symbol": "DOCU", "reportedCurrency": "USD", "cik": "0001261333", "fillingDate": "2023-12-08", "acceptedDate": "2023-12-08 17:15:23", "calendarYear": "2024", "period": "Q3", "netIncome": 38805000, "depreciationAndAmortization": 23324000, "deferredIncomeTax": 3845000, "stockBasedCompensation": 159418000, "changeInWorkingCapital": -16038000, "accountsReceivables": 53099000, "inventory": -13606000, "accountsPayables": 11205000, "otherWorkingCapital": -66736000, "otherNonCashItems": 54823000, "netCashProvidedByOperatingActivities": 264177000, "investmentsInPropertyPlantAndEquipment": -23841000, "acquisitionsNet": -58126000, "purchasesOfInvestments": -29374000, "salesMaturitiesOfInvestments": 87500000, "otherInvestingActivites": 58126000, "netCashUsedForInvestingActivites": 34285000, "debtRepayment": -37083000, "commonStockIssued": 0, "commonStockRepurchased": -75035000, "dividendsPaid": 0, "otherFinancingActivites": -8636000, "netCashUsedProvidedByFinancingActivities": -120754000, "effectOfForexChangesOnCash": -7187000, "netChangeInCash": 170521000, "cashAtEndOfPeriod": 1193501000, "cashAtBeginningOfPeriod": 1022980000, "operatingCashFlow": 264177000, "capitalExpenditure": -23841000, "freeCashFlow": 240336000, "link": "https://www.sec.gov/Archives/edgar/data/1261333/000126133323000103/0001261333-23-000103-index.htm", "finalLink": "https://www.sec.gov/Archives/edgar/data/1261333/000126133323000103/docu-20231031.htm"}, {"date": "2023-07-31", "symbol": "DOCU", "reportedCurrency": "USD", "cik": "0001261333", "fillingDate": "2023-09-07", "acceptedDate": "2023-09-07 17:21:17", "calendarYear": "2024", "period": "Q2", "netIncome": 7395000, "depreciationAndAmortization": 25238000, "deferredIncomeTax": 1797000, "stockBasedCompensation": 151707000, "changeInWorkingCapital": -32322000, "accountsReceivables": -8478000, "inventory": 22088000, "accountsPayables": -11273000, "otherWorkingCapital": -34659000, "otherNonCashItems": 57201000, "netCashProvidedByOperatingActivities": 211016000, "investmentsInPropertyPlantAndEquipment": -27379000, "acquisitionsNet": 37344000, "purchasesOfInvestments": -120662000, "salesMaturitiesOfInvestments": 83318000, "otherInvestingActivites": -37344000, "netCashUsedForInvestingActivites": -64723000, "debtRepayment": 0, "commonStockIssued": 0, "commonStockRepurchased": -30008000, "dividendsPaid": 0, "otherFinancingActivites": -39339000, "netCashUsedProvidedByFinancingActivities": -69347000, "effectOfForexChangesOnCash": 1279000, "netChangeInCash": 78225000, "cashAtEndOfPeriod": 1022980000, "cashAtBeginningOfPeriod": 944755000, "operatingCashFlow": 211016000, "capitalExpenditure": -27379000, "freeCashFlow": 183637000, "link": "https://www.sec.gov/Archives/edgar/data/1261333/000126133323000079/0001261333-23-000079-index.htm", "finalLink": "https://www.sec.gov/Archives/edgar/data/1261333/000126133323000079/docu-20230731.htm"}, {"date": "2023-04-30", "symbol": "DOCU", "reportedCurrency": "USD", "cik": "0001261333", "fillingDate": "2023-06-08", "acceptedDate": "2023-06-08 17:10:43", "calendarYear": "2024", "period": "Q1", "netIncome": 539000, "depreciationAndAmortization": 22867000, "deferredIncomeTax": 1623000, "stockBasedCompensation": 144706000, "changeInWorkingCapital": 9275000, "accountsReceivables": 108281000, "inventory": 0, "accountsPayables": -9021000, "otherWorkingCapital": -89985000, "otherNonCashItems": 54625000, "netCashProvidedByOperatingActivities": 233635000, "investmentsInPropertyPlantAndEquipment": -19057000, "acquisitionsNet": -26869000, "purchasesOfInvestments": -53830000, "salesMaturitiesOfInvestments": 80699000, "otherInvestingActivites": 26869000, "netCashUsedForInvestingActivites": 7812000, "debtRepayment": 0, "commonStockIssued": 0, "commonStockRepurchased": -40472000, "dividendsPaid": 0, "otherFinancingActivites": 19568000, "netCashUsedProvidedByFinancingActivities": -20904000, "effectOfForexChangesOnCash": 1011000, "netChangeInCash": 221554000, "cashAtEndOfPeriod": 944755000, "cashAtBeginningOfPeriod": 723201000, "operatingCashFlow": 233635000, "capitalExpenditure": -19057000, "freeCashFlow": 214578000, "link": "https://www.sec.gov/Archives/edgar/data/1261333/000126133323000070/0001261333-23-000070-index.htm", "finalLink": "https://www.sec.gov/Archives/edgar/data/1261333/000126133323000070/docu-20230430.htm"}, {"date": "2023-01-31", "symbol": "DOCU", "reportedCurrency": "USD", "cik": "0001261333", "fillingDate": "2023-03-27", "acceptedDate": "2023-03-27 10:45:30", "calendarYear": "2023", "period": "Q4", "netIncome": 4863000, "depreciationAndAmortization": 22279000, "deferredIncomeTax": -1348000, "stockBasedCompensation": 145961000, "changeInWorkingCapital": -95823000, "accountsReceivables": -94302000, "inventory": 0, "accountsPayables": -24701000, "otherWorkingCapital": 23180000, "otherNonCashItems": 61125000, "netCashProvidedByOperatingActivities": 137057000, "investmentsInPropertyPlantAndEquipment": -24064000, "acquisitionsNet": 19438000, "purchasesOfInvestments": -131586000, "salesMaturitiesOfInvestments": 112148000, "otherInvestingActivites": -19438000, "netCashUsedForInvestingActivites": -43502000, "debtRepayment": 0, "commonStockIssued": 12678000, "commonStockRepurchased": -17283000, "dividendsPaid": 0, "otherFinancingActivites": -15614000, "netCashUsedProvidedByFinancingActivities": -15614000, "effectOfForexChangesOnCash": 10868000, "netChangeInCash": 88809000, "cashAtEndOfPeriod": 723201000, "cashAtBeginningOfPeriod": 634392000, "operatingCashFlow": 137057000, "capitalExpenditure": -24064000, "freeCashFlow": 112993000, "link": "https://www.sec.gov/Archives/edgar/data/1261333/000126133323000050/0001261333-23-000050-index.htm", "finalLink": "https://www.sec.gov/Archives/edgar/data/1261333/000126133323000050/docu-20230131.htm"}, {"date": "2022-10-31", "symbol": "DOCU", "reportedCurrency": "USD", "cik": "0001261333", "fillingDate": "2022-12-08", "acceptedDate": "2022-12-08 17:14:14", "calendarYear": "2023", "period": "Q3", "netIncome": -29866000, "depreciationAndAmortization": 21532000, "deferredIncomeTax": -23000, "stockBasedCompensation": 140835000, "changeInWorkingCapital": -138433000, "accountsReceivables": -83084000, "inventory": 0, "accountsPayables": 2948000, "otherWorkingCapital": -58297000, "otherNonCashItems": 58492000, "netCashProvidedByOperatingActivities": 52537000, "investmentsInPropertyPlantAndEquipment": -16477000, "acquisitionsNet": -14634000, "purchasesOfInvestments": -106956000, "salesMaturitiesOfInvestments": 121590000, "otherInvestingActivites": 14634000, "netCashUsedForInvestingActivites": -1843000, "debtRepayment": 0, "commonStockIssued": 0, "commonStockRepurchased": -38034000, "dividendsPaid": 0, "otherFinancingActivites": -10505000, "netCashUsedProvidedByFinancingActivities": -48539000, "effectOfForexChangesOnCash": -6612000, "netChangeInCash": -4457000, "cashAtEndOfPeriod": 634392000, "cashAtBeginningOfPeriod": 638849000, "operatingCashFlow": 52537000, "capitalExpenditure": -16477000, "freeCashFlow": 36060000, "link": "https://www.sec.gov/Archives/edgar/data/1261333/000126133322000201/0001261333-22-000201-index.htm", "finalLink": "https://www.sec.gov/Archives/edgar/data/1261333/000126133322000201/docu-20221031.htm"}, {"date": "2022-07-31", "symbol": "DOCU", "reportedCurrency": "USD", "cik": "0001261333", "fillingDate": "2022-09-08", "acceptedDate": "2022-09-08 17:15:58", "calendarYear": "2023", "period": "Q2", "netIncome": -45078000, "depreciationAndAmortization": 21143000, "deferredIncomeTax": 2996000, "stockBasedCompensation": 141207000, "changeInWorkingCapital": -56388000, "accountsReceivables": -38656000, "inventory": 0, "accountsPayables": 18510000, "otherWorkingCapital": -36242000, "otherNonCashItems": 56999000, "netCashProvidedByOperatingActivities": 120879000, "investmentsInPropertyPlantAndEquipment": -15404000, "acquisitionsNet": 67934000, "purchasesOfInvestments": -167058000, "salesMaturitiesOfInvestments": 99124000, "otherInvestingActivites": -67934000, "netCashUsedForInvestingActivites": -83338000, "debtRepayment": -16000, "commonStockIssued": 0, "commonStockRepurchased": -25007000, "dividendsPaid": 0, "otherFinancingActivites": -10430000, "netCashUsedProvidedByFinancingActivities": -35453000, "effectOfForexChangesOnCash": -2860000, "netChangeInCash": -772000, "cashAtEndOfPeriod": 638849000, "cashAtBeginningOfPeriod": 639621000, "operatingCashFlow": 120879000, "capitalExpenditure": -15404000, "freeCashFlow": 105475000, "link": "https://www.sec.gov/Archives/edgar/data/1261333/000126133322000163/0001261333-22-000163-index.htm", "finalLink": "https://www.sec.gov/Archives/edgar/data/1261333/000126133322000163/docu-20220731.htm"}, {"date": "2022-04-30", "symbol": "DOCU", "reportedCurrency": "USD", "cik": "0001261333", "fillingDate": "2022-06-09", "acceptedDate": "2022-06-09 17:09:44", "calendarYear": "2023", "period": "Q1", "netIncome": -27373000, "depreciationAndAmortization": 21301000, "deferredIncomeTax": 72000, "stockBasedCompensation": 110723000, "changeInWorkingCapital": 34940000, "accountsReceivables": 140078000, "inventory": 0, "accountsPayables": -23197000, "otherWorkingCapital": -81941000, "otherNonCashItems": 56623000, "netCashProvidedByOperatingActivities": 196286000, "investmentsInPropertyPlantAndEquipment": -21709000, "acquisitionsNet": 40805000, "purchasesOfInvestments": -131860000, "salesMaturitiesOfInvestments": 91055000, "otherInvestingActivites": -40805000, "netCashUsedForInvestingActivites": -62514000, "debtRepayment": 0, "commonStockIssued": 26089000, "commonStockRepurchased": -24739000, "dividendsPaid": 0, "otherFinancingActivites": 1350000, "netCashUsedProvidedByFinancingActivities": 1350000, "effectOfForexChangesOnCash": -5180000, "netChangeInCash": 129942000, "cashAtEndOfPeriod": 639621000, "cashAtBeginningOfPeriod": 509679000, "operatingCashFlow": 196286000, "capitalExpenditure": -21709000, "freeCashFlow": 174577000, "link": "https://www.sec.gov/Archives/edgar/data/1261333/000126133322000105/0001261333-22-000105-index.htm", "finalLink": "https://www.sec.gov/Archives/edgar/data/1261333/000126133322000105/docu-20220430.htm"}, {"date": "2022-01-31", "symbol": "DOCU", "reportedCurrency": "USD", "cik": "0001261333", "fillingDate": "2022-03-25", "acceptedDate": "2022-03-25 08:53:58", "calendarYear": "2022", "period": "Q4", "netIncome": -30445000, "depreciationAndAmortization": 20750000, "deferredIncomeTax": 3729000, "stockBasedCompensation": 118006000, "changeInWorkingCapital": -80097000, "accountsReceivables": -135349000, "inventory": -4090000, "accountsPayables": 5445000, "otherWorkingCapital": 53897000, "otherNonCashItems": 55850000, "netCashProvidedByOperatingActivities": 87793000, "investmentsInPropertyPlantAndEquipment": -17470000, "acquisitionsNet": -37416000, "purchasesOfInvestments": -82366000, "salesMaturitiesOfInvestments": 94612000, "otherInvestingActivites": 12246000, "netCashUsedForInvestingActivites": -5224000, "debtRepayment": -13071000, "commonStockIssued": 2553000, "commonStockRepurchased": -63412000, "dividendsPaid": 0, "otherFinancingActivites": -60859000, "netCashUsedProvidedByFinancingActivities": -73930000, "effectOfForexChangesOnCash": -3122000, "netChangeInCash": 5517000, "cashAtEndOfPeriod": 509679000, "cashAtBeginningOfPeriod": 504162000, "operatingCashFlow": 87793000, "capitalExpenditure": -17470000, "freeCashFlow": 70323000, "link": "https://www.sec.gov/Archives/edgar/data/1261333/000126133322000049/0001261333-22-000049-index.htm", "finalLink": "https://www.sec.gov/Archives/edgar/data/1261333/000126133322000049/docu-20220131.htm"}, {"date": "2021-10-31", "symbol": "DOCU", "reportedCurrency": "USD", "cik": "0001261333", "fillingDate": "2021-12-06", "acceptedDate": "2021-12-06 17:10:02", "calendarYear": "2022", "period": "Q3", "netIncome": -5676000, "depreciationAndAmortization": 20166000, "deferredIncomeTax": -1110000, "stockBasedCompensation": 109441000, "changeInWorkingCapital": -65634000, "accountsReceivables": -20869000, "inventory": -23072000, "accountsPayables": 16146000, "otherWorkingCapital": -37839000, "otherNonCashItems": 48224000, "netCashProvidedByOperatingActivities": 105411000, "investmentsInPropertyPlantAndEquipment": -15392000, "acquisitionsNet": 37416000, "purchasesOfInvestments": -117384000, "salesMaturitiesOfInvestments": 79968000, "otherInvestingActivites": -37416000, "netCashUsedForInvestingActivites": -52808000, "debtRepayment": -3121000, "commonStockIssued": 32268000, "commonStockRepurchased": -94534000, "dividendsPaid": 0, "otherFinancingActivites": -62266000, "netCashUsedProvidedByFinancingActivities": -65387000, "effectOfForexChangesOnCash": -1909000, "netChangeInCash": -14693000, "cashAtEndOfPeriod": 504164000, "cashAtBeginningOfPeriod": 518857000, "operatingCashFlow": 105411000, "capitalExpenditure": -15392000, "freeCashFlow": 90019000, "link": "https://www.sec.gov/Archives/edgar/data/1261333/000126133321000214/0001261333-21-000214-index.htm", "finalLink": "https://www.sec.gov/Archives/edgar/data/1261333/000126133321000214/docu-20211031.htm"}, {"date": "2021-07-31", "symbol": "DOCU", "reportedCurrency": "USD", "cik": "0001261333", "fillingDate": "2021-09-03", "acceptedDate": "2021-09-03 16:09:55", "calendarYear": "2022", "period": "Q2", "netIncome": -25501000, "depreciationAndAmortization": 20960000, "deferredIncomeTax": -1514000, "stockBasedCompensation": 99458000, "changeInWorkingCapital": 34945000, "accountsReceivables": -34365000, "inventory": 447000, "accountsPayables": 12150000, "otherWorkingCapital": 56713000, "otherNonCashItems": 49321000, "netCashProvidedByOperatingActivities": 177669000, "investmentsInPropertyPlantAndEquipment": -15938000, "acquisitionsNet": -6388000, "purchasesOfInvestments": -88703000, "salesMaturitiesOfInvestments": 76658000, "otherInvestingActivites": -12045000, "netCashUsedForInvestingActivites": -34371000, "debtRepayment": -25030000, "commonStockIssued": 5202000, "commonStockRepurchased": -122522000, "dividendsPaid": 0, "otherFinancingActivites": -117320000, "netCashUsedProvidedByFinancingActivities": -142350000, "effectOfForexChangesOnCash": -1342000, "netChangeInCash": -394000, "cashAtEndOfPeriod": 518858000, "cashAtBeginningOfPeriod": 519252000, "operatingCashFlow": 177669000, "capitalExpenditure": -15938000, "freeCashFlow": 161731000, "link": "https://www.sec.gov/Archives/edgar/data/1261333/000126133321000163/0001261333-21-000163-index.htm", "finalLink": "https://www.sec.gov/Archives/edgar/data/1261333/000126133321000163/docu-20210731.htm"}, {"date": "2021-04-30", "symbol": "DOCU", "reportedCurrency": "USD", "cik": "0001261333", "fillingDate": "2021-06-04", "acceptedDate": "2021-06-04 16:13:42", "calendarYear": "2022", "period": "Q1", "netIncome": -8354000, "depreciationAndAmortization": 20037000, "deferredIncomeTax": 264000, "stockBasedCompensation": 81637000, "changeInWorkingCapital": 9177000, "accountsReceivables": 73205000, "inventory": -13881000, "accountsPayables": -21593000, "otherWorkingCapital": -28554000, "otherNonCashItems": 32836000, "netCashProvidedByOperatingActivities": 135597000, "investmentsInPropertyPlantAndEquipment": -12596000, "acquisitionsNet": 0, "purchasesOfInvestments": -97425000, "salesMaturitiesOfInvestments": 39515000, "otherInvestingActivites": -57910000, "netCashUsedForInvestingActivites": -70506000, "debtRepayment": -36684000, "commonStockIssued": 29783000, "commonStockRepurchased": -106053000, "dividendsPaid": 0, "otherFinancingActivites": -76270000, "netCashUsedProvidedByFinancingActivities": -112954000, "effectOfForexChangesOnCash": 779000, "netChangeInCash": -47084000, "cashAtEndOfPeriod": 519252000, "cashAtBeginningOfPeriod": 566336000, "operatingCashFlow": 135597000, "capitalExpenditure": -12596000, "freeCashFlow": 123001000, "link": "https://www.sec.gov/Archives/edgar/data/1261333/000126133321000108/0001261333-21-000108-index.htm", "finalLink": "https://www.sec.gov/Archives/edgar/data/1261333/000126133321000108/docu-20210430.htm"}, {"date": "2021-01-31", "symbol": "DOCU", "reportedCurrency": "USD", "cik": "0001261333", "fillingDate": "2021-03-31", "acceptedDate": "2021-03-31 17:05:03", "calendarYear": "2021", "period": "Q4", "netIncome": -72412000, "depreciationAndAmortization": 19635000, "deferredIncomeTax": -1360000, "stockBasedCompensation": 83639000, "changeInWorkingCapital": 33144000, "accountsReceivables": -62484000, "inventory": 14763000, "accountsPayables": 8473000, "otherWorkingCapital": 72392000, "otherNonCashItems": -413000, "netCashProvidedByOperatingActivities": 62233000, "investmentsInPropertyPlantAndEquipment": -18251000, "acquisitionsNet": 29084000, "purchasesOfInvestments": -84340000, "salesMaturitiesOfInvestments": 83756000, "otherInvestingActivites": -584000, "netCashUsedForInvestingActivites": -18835000, "debtRepayment": 0, "commonStockIssued": 0, "commonStockRepurchased": -125186000, "dividendsPaid": 0, "otherFinancingActivites": 143459000, "netCashUsedProvidedByFinancingActivities": 143459000, "effectOfForexChangesOnCash": 4214000, "netChangeInCash": 191071000, "cashAtEndOfPeriod": 566336000, "cashAtBeginningOfPeriod": 375265000, "operatingCashFlow": 62233000, "capitalExpenditure": -18251000, "freeCashFlow": 43982000, "link": "https://www.sec.gov/Archives/edgar/data/1261333/000126133321000059/0001261333-21-000059-index.htm", "finalLink": "https://www.sec.gov/Archives/edgar/data/1261333/000126133321000059/docu-20210131.htm"}, {"date": "2020-10-31", "symbol": "DOCU", "reportedCurrency": "USD", "cik": "0001261333", "fillingDate": "2020-12-04", "acceptedDate": "2020-12-04 17:05:09", "calendarYear": "2021", "period": "Q3", "netIncome": -58491000, "depreciationAndAmortization": 19479000, "deferredIncomeTax": -766000, "stockBasedCompensation": 80920000, "changeInWorkingCapital": -24998000, "accountsReceivables": -36583000, "inventory": 708000, "accountsPayables": -2620000, "otherWorkingCapital": 13497000, "otherNonCashItems": 41299000, "netCashProvidedByOperatingActivities": 57443000, "investmentsInPropertyPlantAndEquipment": -19393000, "acquisitionsNet": -29084000, "purchasesOfInvestments": -74282000, "salesMaturitiesOfInvestments": 103366000, "otherInvestingActivites": 29084000, "netCashUsedForInvestingActivites": 9691000, "debtRepayment": 0, "commonStockIssued": 0, "commonStockRepurchased": -113417000, "dividendsPaid": 0, "otherFinancingActivites": -95203000, "netCashUsedProvidedByFinancingActivities": -95203000, "effectOfForexChangesOnCash": -1208000, "netChangeInCash": -29277000, "cashAtEndOfPeriod": 375265000, "cashAtBeginningOfPeriod": 404542000, "operatingCashFlow": 57443000, "capitalExpenditure": -19393000, "freeCashFlow": 38050000, "link": "https://www.sec.gov/Archives/edgar/data/1261333/000126133320000260/0001261333-20-000260-index.htm", "finalLink": "https://www.sec.gov/Archives/edgar/data/1261333/000126133320000260/docu-20201031.htm"}, {"date": "2020-07-31", "symbol": "DOCU", "reportedCurrency": "USD", "cik": "0001261333", "fillingDate": "2020-09-04", "acceptedDate": "2020-09-04 16:13:38", "calendarYear": "2021", "period": "Q2", "netIncome": -64560000, "depreciationAndAmortization": 17937000, "deferredIncomeTax": -180000, "stockBasedCompensation": 68767000, "changeInWorkingCapital": 59596000, "accountsReceivables": 7915000, "inventory": 6936000, "accountsPayables": 8829000, "otherWorkingCapital": 35916000, "otherNonCashItems": 36574000, "netCashProvidedByOperatingActivities": 118134000, "investmentsInPropertyPlantAndEquipment": -18362000, "acquisitionsNet": -180370000, "purchasesOfInvestments": -11908000, "salesMaturitiesOfInvestments": 131345000, "otherInvestingActivites": 119437000, "netCashUsedForInvestingActivites": -79295000, "debtRepayment": 0, "commonStockIssued": 0, "commonStockRepurchased": -87137000, "dividendsPaid": 0, "otherFinancingActivites": -81734000, "netCashUsedProvidedByFinancingActivities": -81734000, "effectOfForexChangesOnCash": 4920000, "netChangeInCash": -37975000, "cashAtEndOfPeriod": 404542000, "cashAtBeginningOfPeriod": 442517000, "operatingCashFlow": 118134000, "capitalExpenditure": -18362000, "freeCashFlow": 99772000, "link": "https://www.sec.gov/Archives/edgar/data/1261333/000126133320000187/0001261333-20-000187-index.htm", "finalLink": "https://www.sec.gov/Archives/edgar/data/1261333/000126133320000187/docu-20200731.htm"}, {"date": "2020-04-30", "symbol": "DOCU", "reportedCurrency": "USD", "cik": "0001261333", "fillingDate": "2020-06-05", "acceptedDate": "2020-06-05 16:03:56", "calendarYear": "2021", "period": "Q1", "netIncome": -47804000, "depreciationAndAmortization": 14039000, "deferredIncomeTax": -104000, "stockBasedCompensation": 53551000, "changeInWorkingCapital": 4432000, "accountsReceivables": 17239000, "inventory": -12274000, "accountsPayables": -2554000, "otherWorkingCapital": 2021000, "otherNonCashItems": 35030000, "netCashProvidedByOperatingActivities": 59144000, "investmentsInPropertyPlantAndEquipment": -26389000, "acquisitionsNet": 0, "purchasesOfInvestments": -3000000, "salesMaturitiesOfInvestments": 199057000, "otherInvestingActivites": 196057000, "netCashUsedForInvestingActivites": 169668000, "debtRepayment": 0, "commonStockIssued": 0, "commonStockRepurchased": -46723000, "dividendsPaid": 0, "otherFinancingActivites": -25498000, "netCashUsedProvidedByFinancingActivities": -25498000, "effectOfForexChangesOnCash": -2280000, "netChangeInCash": 201034000, "cashAtEndOfPeriod": 442517000, "cashAtBeginningOfPeriod": 241483000, "operatingCashFlow": 59144000, "capitalExpenditure": -26389000, "freeCashFlow": 32755000, "link": "https://www.sec.gov/Archives/edgar/data/1261333/000126133320000115/0001261333-20-000115-index.htm", "finalLink": "https://www.sec.gov/Archives/edgar/data/1261333/000126133320000115/docu-20200430.htm"}, {"date": "2020-01-31", "symbol": "DOCU", "reportedCurrency": "USD", "cik": "0001261333", "fillingDate": "2020-03-27", "acceptedDate": "2020-03-27 16:14:10", "calendarYear": "2020", "period": "Q4", "netIncome": -47407000, "depreciationAndAmortization": 13266000, "deferredIncomeTax": 1245000, "stockBasedCompensation": 55605000, "changeInWorkingCapital": -10326000, "accountsReceivables": -78377000, "inventory": 6145000, "accountsPayables": 1543000, "otherWorkingCapital": 60363000, "otherNonCashItems": 33122000, "netCashProvidedByOperatingActivities": 45505000, "investmentsInPropertyPlantAndEquipment": -29975000, "acquisitionsNet": -10470000, "purchasesOfInvestments": -107318000, "salesMaturitiesOfInvestments": 166599000, "otherInvestingActivites": 59281000, "netCashUsedForInvestingActivites": 29306000, "debtRepayment": 0, "commonStockIssued": 0, "commonStockRepurchased": -41216000, "dividendsPaid": 0, "otherFinancingActivites": -31302000, "netCashUsedProvidedByFinancingActivities": -31302000, "effectOfForexChangesOnCash": -137000, "netChangeInCash": 43372000, "cashAtEndOfPeriod": 241483000, "cashAtBeginningOfPeriod": 198111000, "operatingCashFlow": 45505000, "capitalExpenditure": -29975000, "freeCashFlow": 15530000, "link": "https://www.sec.gov/Archives/edgar/data/1261333/000126133320000033/0001261333-20-000033-index.htm", "finalLink": "https://www.sec.gov/Archives/edgar/data/1261333/000126133320000033/docu-20200131.htm"}, {"date": "2019-10-31", "symbol": "DOCU", "reportedCurrency": "USD", "cik": "0001261333", "fillingDate": "2019-12-06", "acceptedDate": "2019-12-06 16:06:15", "calendarYear": "2020", "period": "Q3", "netIncome": -46598000, "depreciationAndAmortization": 12655000, "deferredIncomeTax": 14000, "stockBasedCompensation": 52736000, "changeInWorkingCapital": -50741000, "accountsReceivables": -20812000, "inventory": -11583000, "accountsPayables": 718000, "otherWorkingCapital": -19064000, "otherNonCashItems": 30065000, "netCashProvidedByOperatingActivities": -1869000, "investmentsInPropertyPlantAndEquipment": -12280000, "acquisitionsNet": 6787000, "purchasesOfInvestments": -223048000, "salesMaturitiesOfInvestments": 216261000, "otherInvestingActivites": -6787000, "netCashUsedForInvestingActivites": -19067000, "debtRepayment": 0, "commonStockIssued": 0, "commonStockRepurchased": -39310000, "dividendsPaid": 0, "otherFinancingActivites": -6186000, "netCashUsedProvidedByFinancingActivities": -6186000, "effectOfForexChangesOnCash": 810000, "netChangeInCash": -26312000, "cashAtEndOfPeriod": 198111000, "cashAtBeginningOfPeriod": 224423000, "operatingCashFlow": -1869000, "capitalExpenditure": -12280000, "freeCashFlow": -14149000, "link": "https://www.sec.gov/Archives/edgar/data/1261333/000126133319000108/0001261333-19-000108-index.htm", "finalLink": "https://www.sec.gov/Archives/edgar/data/1261333/000126133319000108/q32010q.htm"}, {"date": "2019-07-31", "symbol": "DOCU", "reportedCurrency": "USD", "cik": "0001261333", "fillingDate": "2019-09-06", "acceptedDate": "2019-09-06 16:23:25", "calendarYear": "2020", "period": "Q2", "netIncome": -68632000, "depreciationAndAmortization": 12290000, "deferredIncomeTax": -24000, "stockBasedCompensation": 55792000, "changeInWorkingCapital": 67000, "accountsReceivables": -21518000, "inventory": 4668000, "accountsPayables": 1306000, "otherWorkingCapital": 15611000, "otherNonCashItems": 26912000, "netCashProvidedByOperatingActivities": 26405000, "investmentsInPropertyPlantAndEquipment": -14554000, "acquisitionsNet": 3683000, "purchasesOfInvestments": -155675000, "salesMaturitiesOfInvestments": 151992000, "otherInvestingActivites": -3683000, "netCashUsedForInvestingActivites": -18237000, "debtRepayment": 0, "commonStockIssued": 0, "commonStockRepurchased": -29841000, "dividendsPaid": 0, "otherFinancingActivites": -19647000, "netCashUsedProvidedByFinancingActivities": -19647000, "effectOfForexChangesOnCash": -741000, "netChangeInCash": -12220000, "cashAtEndOfPeriod": 224423000, "cashAtBeginningOfPeriod": 236643000, "operatingCashFlow": 26405000, "capitalExpenditure": -14554000, "freeCashFlow": 11851000, "link": "https://www.sec.gov/Archives/edgar/data/1261333/000126133319000077/0001261333-19-000077-index.htm", "finalLink": "https://www.sec.gov/Archives/edgar/data/1261333/000126133319000077/q22010q.htm"}, {"date": "2019-04-30", "symbol": "DOCU", "reportedCurrency": "USD", "cik": "0001261333", "fillingDate": "2019-06-07", "acceptedDate": "2019-06-07 16:20:56", "calendarYear": "2020", "period": "Q1", "netIncome": -45722000, "depreciationAndAmortization": 16099000, "deferredIncomeTax": 52000, "stockBasedCompensation": 42271000, "changeInWorkingCapital": 13352000, "accountsReceivables": 57414000, "inventory": -6530000, "accountsPayables": 282000, "otherWorkingCapital": -37814000, "otherNonCashItems": 19603000, "netCashProvidedByOperatingActivities": 45655000, "investmentsInPropertyPlantAndEquipment": -15237000, "acquisitionsNet": 0, "purchasesOfInvestments": -390711000, "salesMaturitiesOfInvestments": 92457000, "otherInvestingActivites": -298254000, "netCashUsedForInvestingActivites": -313491000, "debtRepayment": 0, "commonStockIssued": 0, "commonStockRepurchased": -56137000, "dividendsPaid": 0, "otherFinancingActivites": -13320000, "netCashUsedProvidedByFinancingActivities": -13320000, "effectOfForexChangesOnCash": -379000, "netChangeInCash": -281535000, "cashAtEndOfPeriod": 236643000, "cashAtBeginningOfPeriod": 518178000, "operatingCashFlow": 45655000, "capitalExpenditure": -15237000, "freeCashFlow": 30418000, "link": "https://www.sec.gov/Archives/edgar/data/1261333/000126133319000041/0001261333-19-000041-index.htm", "finalLink": "https://www.sec.gov/Archives/edgar/data/1261333/000126133319000041/q12010q.htm"}, {"date": "2019-01-31", "symbol": "DOCU", "reportedCurrency": "USD", "cik": "0001261333", "fillingDate": "2019-03-26", "acceptedDate": "2019-03-26 17:28:06", "calendarYear": "2019", "period": "Q4", "netIncome": -66244000, "depreciationAndAmortization": 12003000, "deferredIncomeTax": 2346000, "stockBasedCompensation": 49271000, "changeInWorkingCapital": 15299000, "accountsReceivables": -43937000, "inventory": 1790000, "accountsPayables": -1390000, "otherWorkingCapital": 58836000, "otherNonCashItems": 21462000, "netCashProvidedByOperatingActivities": 34137000, "investmentsInPropertyPlantAndEquipment": -11317000, "acquisitionsNet": 0, "purchasesOfInvestments": -415132000, "salesMaturitiesOfInvestments": 0, "otherInvestingActivites": -415132000, "netCashUsedForInvestingActivites": -426449000, "debtRepayment": -319000, "commonStockIssued": 0, "commonStockRepurchased": -215332000, "dividendsPaid": 0, "otherFinancingActivites": -180736000, "netCashUsedProvidedByFinancingActivities": -181055000, "effectOfForexChangesOnCash": -2955000, "netChangeInCash": -576322000, "cashAtEndOfPeriod": 518178000, "cashAtBeginningOfPeriod": 1094500000, "operatingCashFlow": 34137000, "capitalExpenditure": -11317000, "freeCashFlow": 22820000, "link": "https://www.sec.gov/Archives/edgar/data/1261333/000126133319000012/0001261333-19-000012-index.htm", "finalLink": "https://www.sec.gov/Archives/edgar/data/1261333/000126133319000012/fy1910k.htm"}, {"date": "2018-10-31", "symbol": "DOCU", "reportedCurrency": "USD", "cik": "0001261333", "fillingDate": "2018-12-07", "acceptedDate": "2018-12-07 16:12:00", "calendarYear": "2019", "period": "Q3", "netIncome": -52813000, "depreciationAndAmortization": 10343000, "deferredIncomeTax": -7335000, "stockBasedCompensation": 51748000, "changeInWorkingCapital": -10368000, "accountsReceivables": -14019000, "inventory": 4619000, "accountsPayables": -956000, "otherWorkingCapital": -12000, "otherNonCashItems": 12686000, "netCashProvidedByOperatingActivities": 4261000, "investmentsInPropertyPlantAndEquipment": -8576000, "acquisitionsNet": -218779000, "purchasesOfInvestments": 0, "salesMaturitiesOfInvestments": 0, "otherInvestingActivites": 0, "netCashUsedForInvestingActivites": -227355000, "debtRepayment": 0, "commonStockIssued": 0, "commonStockRepurchased": -67563000, "dividendsPaid": 0, "otherFinancingActivites": 498070000, "netCashUsedProvidedByFinancingActivities": 498070000, "effectOfForexChangesOnCash": 362000, "netChangeInCash": 275338000, "cashAtEndOfPeriod": 1094500000, "cashAtBeginningOfPeriod": 819162000, "operatingCashFlow": 4261000, "capitalExpenditure": -8576000, "freeCashFlow": -4315000, "link": "https://www.sec.gov/Archives/edgar/data/1261333/000126133318000027/0001261333-18-000027-index.htm", "finalLink": "https://www.sec.gov/Archives/edgar/data/1261333/000126133318000027/q31910q.htm"}, {"date": "2018-07-31", "symbol": "DOCU", "reportedCurrency": "USD", "cik": "0001261333", "fillingDate": "2018-09-06", "acceptedDate": "2018-09-06 17:05:24", "calendarYear": "2019", "period": "Q2", "netIncome": -36714000, "depreciationAndAmortization": 7081000, "deferredIncomeTax": -6000, "stockBasedCompensation": 40165000, "changeInWorkingCapital": 5369000, "accountsReceivables": -4237000, "inventory": 1615000, "accountsPayables": 2184000, "otherWorkingCapital": 5807000, "otherNonCashItems": 6800000, "netCashProvidedByOperatingActivities": 22695000, "investmentsInPropertyPlantAndEquipment": -4336000, "acquisitionsNet": 0, "purchasesOfInvestments": 0, "salesMaturitiesOfInvestments": 0, "otherInvestingActivites": 0, "netCashUsedForInvestingActivites": -4336000, "debtRepayment": 0, "commonStockIssued": 529305000, "commonStockRepurchased": 0, "dividendsPaid": 0, "otherFinancingActivites": 530480000, "netCashUsedProvidedByFinancingActivities": 530480000, "effectOfForexChangesOnCash": 527000, "netChangeInCash": 549366000, "cashAtEndOfPeriod": 819162000, "cashAtBeginningOfPeriod": 269796000, "operatingCashFlow": 22695000, "capitalExpenditure": -4336000, "freeCashFlow": 18359000, "link": "https://www.sec.gov/Archives/edgar/data/1261333/000126133318000017/0001261333-18-000017-index.htm", "finalLink": "https://www.sec.gov/Archives/edgar/data/1261333/000126133318000017/q21910q.htm"}, {"date": "2018-04-30", "symbol": "DOCU", "reportedCurrency": "USD", "cik": "0001261333", "fillingDate": "2018-06-08", "acceptedDate": "2018-06-08 16:48:39", "calendarYear": "2019", "period": "Q1", "netIncome": -270687000, "depreciationAndAmortization": 8600000, "deferredIncomeTax": -6000, "stockBasedCompensation": 269794000, "changeInWorkingCapital": -4180000, "accountsReceivables": 19622000, "inventory": -231000, "accountsPayables": -7218000, "otherWorkingCapital": -16353000, "otherNonCashItems": 11471000, "netCashProvidedByOperatingActivities": 14992000, "investmentsInPropertyPlantAndEquipment": -6184000, "acquisitionsNet": 0, "purchasesOfInvestments": 0, "salesMaturitiesOfInvestments": 0, "otherInvestingActivites": 0, "netCashUsedForInvestingActivites": -6184000, "debtRepayment": 0, "commonStockIssued": 0, "commonStockRepurchased": 0, "dividendsPaid": 0, "otherFinancingActivites": 5621000, "netCashUsedProvidedByFinancingActivities": 5621000, "effectOfForexChangesOnCash": -2069000, "netChangeInCash": 12360000, "cashAtEndOfPeriod": 269796000, "cashAtBeginningOfPeriod": 257436000, "operatingCashFlow": 14992000, "capitalExpenditure": -6184000, "freeCashFlow": 8808000, "link": "https://www.sec.gov/Archives/edgar/data/1261333/000126133318000009/0001261333-18-000009-index.htm", "finalLink": "https://www.sec.gov/Archives/edgar/data/1261333/000126133318000009/q11910q.htm"}, {"date": "2018-01-31", "symbol": "DOCU", "reportedCurrency": "USD", "cik": "0001261333", "fillingDate": "2018-01-31", "acceptedDate": "2018-01-30 19:00:00", "calendarYear": "2018", "period": "Q4", "netIncome": -6352000, "depreciationAndAmortization": 8017000, "deferredIncomeTax": -1054000, "stockBasedCompensation": 6234000, "changeInWorkingCapital": 20319000, "accountsReceivables": -41039000, "inventory": -1025000, "accountsPayables": 8409000, "otherWorkingCapital": 53974000, "otherNonCashItems": 4796000, "netCashProvidedByOperatingActivities": 31960000, "investmentsInPropertyPlantAndEquipment": -3237000, "acquisitionsNet": -299000, "purchasesOfInvestments": 0, "salesMaturitiesOfInvestments": 0, "otherInvestingActivites": 0, "netCashUsedForInvestingActivites": -3536000, "debtRepayment": 0, "commonStockIssued": 0, "commonStockRepurchased": 0, "dividendsPaid": 0, "otherFinancingActivites": 4172000, "netCashUsedProvidedByFinancingActivities": 4172000, "effectOfForexChangesOnCash": 2674000, "netChangeInCash": 35270000, "cashAtEndOfPeriod": 257436000, "cashAtBeginningOfPeriod": 222166000, "operatingCashFlow": 31960000, "capitalExpenditure": -3237000, "freeCashFlow": 28723000, "link": "", "finalLink": ""}, {"date": "2017-10-31", "symbol": "DOCU", "reportedCurrency": "USD", "cik": "0001261333", "fillingDate": "2017-10-31", "acceptedDate": "2017-10-30 20:00:00", "calendarYear": "2018", "period": "Q3", "netIncome": -14505000, "depreciationAndAmortization": 8318000, "deferredIncomeTax": 58000, "stockBasedCompensation": 6595000, "changeInWorkingCapital": 1616000, "accountsReceivables": -146000, "inventory": -3240000, "accountsPayables": 726000, "otherWorkingCapital": 4276000, "otherNonCashItems": 9536000, "netCashProvidedByOperatingActivities": 11618000, "investmentsInPropertyPlantAndEquipment": -4603000, "acquisitionsNet": 0, "purchasesOfInvestments": 0, "salesMaturitiesOfInvestments": 0, "otherInvestingActivites": 0, "netCashUsedForInvestingActivites": -4603000, "debtRepayment": 0, "commonStockIssued": 0, "commonStockRepurchased": 0, "dividendsPaid": 0, "otherFinancingActivites": 8047000, "netCashUsedProvidedByFinancingActivities": 8047000, "effectOfForexChangesOnCash": -571000, "netChangeInCash": 14491000, "cashAtEndOfPeriod": 222166000, "cashAtBeginningOfPeriod": 207675000, "operatingCashFlow": 11618000, "capitalExpenditure": -4603000, "freeCashFlow": 7015000, "link": "", "finalLink": ""}, {"date": "2017-07-31", "symbol": "DOCU", "reportedCurrency": "USD", "cik": "0001261333", "fillingDate": "2017-07-31", "acceptedDate": "2017-07-30 20:00:00", "calendarYear": "2018", "period": "Q2", "netIncome": -12037000, "depreciationAndAmortization": 7699000, "deferredIncomeTax": 13000, "stockBasedCompensation": 8512000, "changeInWorkingCapital": 1656000, "accountsReceivables": 1531000, "inventory": 3454000, "accountsPayables": -4146000, "otherWorkingCapital": 817000, "otherNonCashItems": 6255000, "netCashProvidedByOperatingActivities": 12098000, "investmentsInPropertyPlantAndEquipment": -4319000, "acquisitionsNet": 0, "purchasesOfInvestments": 0, "salesMaturitiesOfInvestments": 0, "otherInvestingActivites": 467000, "netCashUsedForInvestingActivites": -3852000, "debtRepayment": 0, "commonStockIssued": 0, "commonStockRepurchased": 0, "dividendsPaid": 0, "otherFinancingActivites": 7679000, "netCashUsedProvidedByFinancingActivities": 7679000, "effectOfForexChangesOnCash": 1659000, "netChangeInCash": 17584000, "cashAtEndOfPeriod": 207675000, "cashAtBeginningOfPeriod": 190091000, "operatingCashFlow": 12098000, "capitalExpenditure": -4319000, "freeCashFlow": 7779000, "link": "", "finalLink": ""}, {"date": "2017-04-30", "symbol": "DOCU", "reportedCurrency": "USD", "cik": "0001261333", "fillingDate": "2017-04-30", "acceptedDate": "2017-04-30 00:00:00", "calendarYear": "2018", "period": "Q1", "netIncome": -19382000, "depreciationAndAmortization": 7686000, "deferredIncomeTax": -13000, "stockBasedCompensation": 8406000, "changeInWorkingCapital": -3604000, "accountsReceivables": 11577000, "inventory": -5770000, "accountsPayables": -2125000, "otherWorkingCapital": -7286000, "otherNonCashItems": 6210000, "netCashProvidedByOperatingActivities": -697000, "investmentsInPropertyPlantAndEquipment": -6770000, "acquisitionsNet": 0, "purchasesOfInvestments": 0, "salesMaturitiesOfInvestments": 0, "otherInvestingActivites": 0, "netCashUsedForInvestingActivites": -6770000, "debtRepayment": 0, "commonStockIssued": 0, "commonStockRepurchased": 0, "dividendsPaid": 0, "otherFinancingActivites": 5830000, "netCashUsedProvidedByFinancingActivities": 5830000, "effectOfForexChangesOnCash": 484000, "netChangeInCash": -1153000, "cashAtEndOfPeriod": 190091000, "cashAtBeginningOfPeriod": 191244000, "operatingCashFlow": -697000, "capitalExpenditure": -6770000, "freeCashFlow": -7467000, "link": "", "finalLink": ""}]